geodz/__init__.py
geodz/admin.py
geodz/apps.py
geodz/models.py
geodz/tests.py
geodz/views.py
geodz/fixtures/initial_data.json
geodz/locale/fr/LC_MESSAGES/django.mo
geodz/locale/fr/LC_MESSAGES/django.po
geodz/migrations/0001_initial.py
geodz/migrations/0002_auto_20150428_2335.py
geodz/migrations/__init__.py
geodz/south_migrations/0001_initial.py
geodz/south_migrations/__init__.py
geodz/static/img/gmaps.png
django_geodz-0.6.2.dist-info/LICENSE
django_geodz-0.6.2.dist-info/METADATA
django_geodz-0.6.2.dist-info/WHEEL
django_geodz-0.6.2.dist-info/top_level.txt
django_geodz-0.6.2.dist-info/RECORD
