Metadata-Version: 2.1
Name: django-geodz
Version: 0.6.2
Summary: A simple django app that provides out of the box algerian province and municipality models and their respective data fixtures.
Home-page: https://www.github.com/redouane/django-geodz
Author: Redouane Zait
Author-email: redouanezait@gmail.com
License: BSD License
Platform: UNKNOWN
Classifier: Environment :: Web Environment
Classifier: Framework :: Django
Classifier: Intended Audience :: Developers
Classifier: License :: OSI Approved :: BSD License
Classifier: Operating System :: OS Independent
Classifier: Programming Language :: Python
Classifier: Programming Language :: Python :: 2
Classifier: Programming Language :: Python :: 2.6
Classifier: Programming Language :: Python :: 2.7
Classifier: Topic :: Utilities
Requires-Dist: Django
Requires-Dist: django-geoposition
